yaml_kit/__init__.py
yaml_kit/command.py
yaml_kit/config.py
yaml_kit-0.0.2.post1.dist-info/licenses/LICENSE
yaml_kit-0.0.2.post1.dist-info/METADATA
yaml_kit-0.0.2.post1.dist-info/WHEEL
yaml_kit-0.0.2.post1.dist-info/top_level.txt
yaml_kit-0.0.2.post1.dist-info/RECORD
