Metadata-Version: 2.4
Name: yaml-kit
Version: 0.0.2.post1
Summary: A package for creating and modifying YAML files.
Author-email: Jake Vasilakes <jvasialkes@gmail.com>
License-Expression: MIT
Project-URL: Homepage, https://github.com/jvasilakes/experiment-config
Classifier: Programming Language :: Python :: 3
Classifier: Operating System :: OS Independent
Requires-Python: >=3.8
License-File: LICENSE
Requires-Dist: colorama>=0.4
Requires-Dist: ruamel.yaml>=0.18
Dynamic: license-file
